resoterre/__init__.py
resoterre/cli.py
resoterre/resoterre.py
resoterre/ml/data_loader_utils.py
resoterre/ml/network_manager.py
resoterre/ml/neural_networks_basic.py
resoterre/ml/neural_networks_unet.py
resoterre-0.1.2.dist-info/entry_points.txt
resoterre-0.1.2.dist-info/licenses/LICENSE
resoterre-0.1.2.dist-info/WHEEL
resoterre-0.1.2.dist-info/METADATA
resoterre-0.1.2.dist-info/RECORD
