Metadata-Version: 2.4
Name: resoterre
Version: 0.1.2
Summary: Machine learning tools and extensions for climate science.
Keywords: resoterre
Author-email: Blaise Gauvin St-Denis <gauvin-st-denis.blaise@ouranos.ca>
Maintainer-email: Blaise Gauvin St-Denis <gauvin-st-denis.blaise@ouranos.ca>, Trevor James Smith <smith.trevorj@ouranos.ca>
Requires-Python: >=3.10.0
Classifier: Development Status :: 2 - Pre-Alpha
Classifier: Intended Audience :: Developers
Classifier: Intended Audience :: Science/Research
Classifier: License :: OSI Approved :: Apache Software License
Classifier: Natural Language :: English
Classifier: Operating System :: OS Independent
Classifier: Programming Language :: Python :: 3
Classifier: Programming Language :: Python :: 3 :: Only
Classifier: Programming Language :: Python :: 3.10
Classifier: Programming Language :: Python :: 3.11
Classifier: Programming Language :: Python :: 3.12
Classifier: Programming Language :: Python :: 3.13
Classifier: Programming Language :: Python :: Implementation :: CPython
Classifier: Topic :: Scientific/Engineering :: Artificial Intelligence
Classifier: Topic :: Scientific/Engineering :: Atmospheric Science
Classifier: Typing :: Typed
License-File: LICENSE
Requires-Dist: click >=8.2.0
Requires-Dist: numpy >=1.26.4
Requires-Dist: scikit-learn >=1.6.1
Requires-Dist: torch >=2.7.1
Requires-Dist: resoterre[dev] ; extra == "all"
Requires-Dist: resoterre[docs] ; extra == "all"
Requires-Dist: bump-my-version >=1.2.0 ; extra == "dev"
Requires-Dist: coverage >=7.5.0 ; extra == "dev"
Requires-Dist: flake8 >=7.2.0 ; extra == "dev"
Requires-Dist: flake8-rst-docstrings >=0.3.0 ; extra == "dev"
Requires-Dist: flit >=3.12.0,<4.0 ; extra == "dev"
Requires-Dist: mypy >=1.14.1 ; extra == "dev"
Requires-Dist: numpydoc >=1.8.0 ; extra == "dev"
Requires-Dist: pip >=25.1.1 ; extra == "dev"
Requires-Dist: pre-commit >=3.5.0 ; extra == "dev"
Requires-Dist: pytest >=8.3.2 ; extra == "dev"
Requires-Dist: pytest-cov >=5.0.0 ; extra == "dev"
Requires-Dist: ruff >=0.12.0 ; extra == "dev"
Requires-Dist: tox >=4.26.0 ; extra == "dev"
Requires-Dist: types-click >=7.1.0 ; extra == "dev"
Requires-Dist: watchdog >=4.0.0 ; extra == "dev"
Requires-Dist: ipykernel ; extra == "docs"
Requires-Dist: ipython ; extra == "docs"
Requires-Dist: jupyter_client ; extra == "docs"
Requires-Dist: nbsphinx >=0.9.5 ; extra == "docs"
Requires-Dist: sphinx >=7.1.0 ; extra == "docs"
Requires-Dist: sphinx-click ; extra == "docs"
Requires-Dist: sphinx-codeautolink >=0.16.2 ; extra == "docs"
Requires-Dist: sphinx-copybutton ; extra == "docs"
Requires-Dist: sphinx-intl ; extra == "docs"
Requires-Dist: sphinx-rtd-theme >=1.0 ; extra == "docs"
Project-URL: About Ouranos, https://ouranos.ca/en/
Project-URL: Changelog, https://resoterre.readthedocs.io/en/stable/changelog.html
Project-URL: Homepage, https://resoterre.readthedocs.io/
Project-URL: Issue tracker, https://github.com/Ouranosinc/resoterre/issues
Project-URL: Source, https://github.com/Ouranosinc/resoterre
Provides-Extra: all
Provides-Extra: dev
Provides-Extra: docs
